{"brand": "ESSENTIALS", "destination": {"path": "", "url": "/products/essentials-c17jkw17-jug-kettle-white-10156975.html"}, "locatorComponent": {"path": "listview.pdp-link.a.link", "position": 1, "section": "productTile"}, "price": "8.99", "product": "C17JKW17 Jug Kettle - White", "properties": {"Anti-limescale filter": "", "Capacity:": "1.7 litres", "Power:": "2200 W", "Water level indicator": ""}, "text": "ESSENTIALS C17JKW17 Jug Kettle - White", "type": "link", "variant": {"experience": "desktop", "name": ""}}
{"brand": "BREVILLE", "destination": {"path": "", "url": "/products/breville-hot-cup-vkj318-fivecup-hot-water-dispenser-black-04013995.html"}, "locatorComponent": {"path": "listview.pdp-link.a.link", "position": 1, "section": "productTile"}, "price": "64.99", "product": "Hot Cup VKJ318 Five-Cup Hot Water Dispenser - Black", "properties": {"Capacity:": "2 litres", "Power:": "3000 W", "Water level indicator": ""}, "text": "BREVILLE Hot Cup VKJ318 Five-Cup Hot Water Dispenser - Black", "type": "link", "variant": {"experience": "desktop", "name": ""}}
{"brand": "BREVILLE", "destination": {"path": "", "url": "/products/breville-obliq-vkt178-jug-kettle-grey-10226052.html"}, "locatorComponent": {"path": "listview.pdp-link.a.link", "position": 1, "section": "productTile"}, "price": "34.99", "product": "Obliq VKT178 Jug Kettle - Grey", "properties": {"360-degree rotational base": "", "Anti-limescale filter": "", "Capacity:": "1.7 litres", "Power:": "3000 W", "Water level indicator": ""}, "text": "BREVILLE Obliq VKT178 Jug Kettle - Grey", "type": "link", "variant": {"experience": "desktop", "name": ""}}
{"brand": "BREVILLE", "destination": {"path": "", "url": "/products/breville-obliq-vkt179-jug-kettle-black-10226066.html"}, "locatorComponent": {"path": "listview.pdp-link.a.link", "position": 1, "section": "productTile"}, "price": "34.99", "product": "Obliq VKT179 Jug Kettle - Black", "properties": {"360-degree rotational base": "", "Anti-limescale filter": "", "Capacity:": "1.7 litres", "Power:": "3000 W", "Water level indicator": ""}, "text": "BREVILLE Obliq VKT179 Jug Kettle - Black", "type": "link", "variant": {"experience": "desktop", "name": ""}}
{"brand": "DELONGHI", "destination": {"path": "", "url": "/products/delonghi-icona-metallics-kbot3001.gy-jug-kettle-grey-10210407.html"}, "locatorComponent": {"path": "listview.pdp-link.a.link", "position": 1, "section": "productTile"}, "price": "54.99", "product": "Icona Metallics KBOT3001.GY Jug Kettle - Grey", "properties": {"360-degree rotational base": "", "Anti-limescale filter": "", "Capacity:": "1.7 litres", "Power:": "3000 W", "Water level indicator": ""}, "text": "DELONGHI Icona Metallics KBOT3001.GY Jug Kettle - Grey", "type": "link", "variant": {"experience": "desktop", "name": ""}}
{"brand": "BREVILLE", "destination": {"path": "", "url": "/products/breville-obliq-vkt180-jug-kettle-white-10225894.html"}, "locatorComponent": {"path": "listview.pdp-link.a.link", "position": 1, "section": "productTile"}, "price": "34.99", "product": "Obliq VKT180 Jug Kettle - White", "properties": {"360-degree rotational base": "", "Anti-limescale filter": "", "Capacity:": "1.7 litres", "Power:": "3000 W", "Water level indicator": ""}, "text": "BREVILLE Obliq VKT180 Jug Kettle - White", "type": "link", "variant": {"experience": "desktop", "name": ""}}
{"brand": "LOGIK", "destination": {"path": "", "url": "/products/logik-l17jbs17-jug-kettle-stainless-steel-10156976.html"}, "locatorComponent": {"path": "listview.pdp-link.a.link", "position": 1, "section": "productTile"}, "price": "14.99", "product": "L17JBS17 Jug Kettle - Stainless Steel", "properties": {"360-degree rotational base": "", "Capacity:": "1.7 litres", "Power:": "2200 W", "Water level indicator": ""}, "text": "LOGIK L17JBS17 Jug Kettle - Stainless Steel", "type": "link", "variant": {"experience": "desktop", "name": ""}}
{"brand": "LOGIK", "destination": {"path": "", "url": "/products/logik-l17pkb21-jug-kettle-black-10220903.html"}, "locatorComponent": {"path": "listview.pdp-link.a.link", "position": 1, "section": "productTile"}, "price": "14.99", "product": "L17PKB21 Jug Kettle - Black", "properties": {"360-degree rotational base": "", "Anti-limescale filter": "", "Capacity:": "1.7 litres", "Power:": "3000 W", "Water level indicator": ""}, "text": "LOGIK L17PKB21 Jug Kettle - Black", "type": "link", "variant": {"experience": "desktop", "name": ""}}
{"brand": "BREVILLE", "destination": {"path": "", "url": "/products/breville-obliq-vkt203-jug-kettle-vanilla-cream-10226101.html"}, "locatorComponent": {"path": "listview.pdp-link.a.link", "position": 1, "section": "productTile"}, "price": "34.99", "product": "Obliq VKT203 Jug Kettle - Vanilla Cream", "properties": {"360-degree rotational base": "", "Anti-limescale filter": "", "Capacity:": "1.7 litres", "Power:": "3000 W", "Water level indicator": ""}, "text": "BREVILLE Obliq VKT203 Jug Kettle - Vanilla Cream", "type": "link", "variant": {"experience": "desktop", "name": ""}}
{"brand": "DELONGHI", "destination": {"path": "", "url": "/products/delonghi-icona-capitals-kboc3001.w-jug-kettle-white-10181424.html"}, "locatorComponent": {"path": "listview.pdp-link.a.link", "position": 1, "section": "productTile"}, "price": "109.00", "product": "Icona Capitals KBOC3001.W Jug Kettle - White", "properties": {"360-degree rotational base": "", "Anti-limescale filter": "", "Capacity:": "1.7 litres", "Power:": "3000 W", "Water level indicator": ""}, "text": "DELONGHI Icona Capitals KBOC3001.W Jug Kettle - White", "type": "link", "variant": {"experience": "desktop", "name": ""}}
{"brand": "RUSSELL", "destination": {"path": "", "url": "/products/russell-hobbs-retro-21675-jug-kettle-silver-10194632.html"}, "locatorComponent": {"path": "listview.pdp-link.a.link", "position": 1, "section": "productTile"}, "price": "49.99", "product": "HOBBS Retro 21675 Jug Kettle - Silver", "properties": {"360-degree rotational base": "", "Capacity:": "1.7 litres", "Power:": "3000 W", "Water level indicator": ""}, "text": "RUSSELL HOBBS Retro 21675 Jug Kettle - Silver", "type": "link", "variant": {"experience": "desktop", "name": ""}}
{"brand": "RUSSELL", "destination": {"path": "", "url": "/products/russell-hobbs-classic-26080-jug-kettle-black-and-glass-10226463.html"}, "locatorComponent": {"path": "listview.pdp-link.a.link", "position": 1, "section": "productTile"}, "price": "34.99", "product": "HOBBS Classic 26080 Jug Kettle - Black & Glass", "properties": {"360-degree rotational base": "", "Anti-limescale filter": "", "Capacity:": "1.7 litres", "Power:": "3000 W", "Water level indicator": ""}, "text": "RUSSELL HOBBS Classic 26080 Jug Kettle - Black & Glass", "type": "link", "variant": {"experience": "desktop", "name": ""}}
{"brand": "BREVILLE", "destination": {"path": "", "url": "/products/breville-hot-cup-vkt124-8cup-hot-water-dispenser-black-10162318.html"}, "locatorComponent": {"path": "listview.pdp-link.a.link", "position": 1, "section": "productTile"}, "price": "39.99", "product": "Hot Cup VKT124 8-cup Hot Water Dispenser - Black", "properties": {"Anti-limescale filter": "", "Capacity:": "1.7 litres", "Power:": "3000 W", "Water level indicator": ""}, "text": "BREVILLE Hot Cup VKT124 8-cup Hot Water Dispenser - Black", "type": "link", "variant": {"experience": "desktop", "name": ""}}
{"brand": "BREVILLE", "destination": {"path": "", "url": "/products/breville-mostra-vkt140-jug-kettle-cream-10194637.html"}, "locatorComponent": {"path": "listview.pdp-link.a.link", "position": 1, "section": "productTile"}, "price": "44.99", "product": "Mostra VKT140 Jug Kettle - Cream", "properties": {"360-degree rotational base": "", "Anti-limescale filter": "", "Capacity:": "1.7 litres", "Power:": "3000 W", "Water level indicator": ""}, "text": "BREVILLE Mostra VKT140 Jug Kettle - Cream", "type": "link", "variant": {"experience": "desktop", "name": ""}}
{"brand": "DELONGHI", "destination": {"path": "", "url": "/products/delonghi-icona-capitals-kboc3001.bl-jug-kettle-blue-10181423.html"}, "locatorComponent": {"path": "listview.pdp-link.a.link", "position": 1, "section": "productTile"}, "price": "109.00", "product": "Icona Capitals KBOC3001.BL Jug Kettle - Blue", "properties": {"360-degree rotational base": "", "Anti-limescale filter": "", "Capacity:": "1.7 litres", "Power:": "3000 W", "Water level indicator": ""}, "text": "DELONGHI Icona Capitals KBOC3001.BL Jug Kettle - Blue", "type": "link", "variant": {"experience": "desktop", "name": ""}}
{"brand": "KENWOOD", "destination": {"path": "", "url": "/products/kenwood-abbey-lux-zjp05aodg-jug-kettle-matte-black-10226453.html"}, "locatorComponent": {"path": "listview.pdp-link.a.link", "position": 1, "section": "productTile"}, "price": "29.99", "product": "Abbey Lux ZJP05AODG Jug Kettle - Matte Black", "properties": {"360-degree rotational base": "", "Anti-limescale filter": "", "Capacity:": "1.7 litres", "Power:": "3000 W", "Water level indicator": ""}, "text": "KENWOOD Abbey Lux ZJP05AODG Jug Kettle - Matte Black", "type": "link", "variant": {"experience": "desktop", "name": ""}}
{"brand": "BREVILLE", "destination": {"path": "", "url": "/products/breville-obliq-vkt202-jug-kettle-navy-blue-10227227.html"}, "locatorComponent": {"path": "listview.pdp-link.a.link", "position": 1, "section": "productTile"}, "price": "34.99", "product": "Obliq VKT202 Jug Kettle - Navy Blue", "properties": {"360-degree rotational base": "", "Anti-limescale filter": "", "Capacity:": "1.7 litres", "Power:": "3000 W", "Water level indicator": ""}, "text": "BREVILLE Obliq VKT202 Jug Kettle - Navy Blue", "type": "link", "variant": {"experience": "desktop", "name": ""}}
{"brand": "BREVILLE", "destination": {"path": "", "url": "/products/breville-obliq-vkt204-jug-kettle-lilac-and-pale-gold-10225916.html"}, "locatorComponent": {"path": "listview.pdp-link.a.link", "position": 1, "section": "productTile"}, "price": "34.99", "product": "Obliq VKT204 Jug Kettle - Lilac & Pale Gold", "properties": {"360-degree rotational base": "", "Anti-limescale filter": "", "Capacity:": "1.7 litres", "Power:": "3000 W", "Water level indicator": ""}, "text": "BREVILLE Obliq VKT204 Jug Kettle - Lilac & Pale Gold", "type": "link", "variant": {"experience": "desktop", "name": ""}}
{"brand": "KITCHENAID", "destination": {"path": "", "url": "/products/kitchenaid-artisan-5kek1522bac-traditional-kettle-almond-cream-10156849.html"}, "locatorComponent": {"path": "listview.pdp-link.a.link", "position": 1, "section": "productTile"}, "price": "129.00", "product": "Artisan 5KEK1522BAC Traditional Kettle - Almond Cream", "properties": {"360-degree rotational base": "", "Anti-limescale filter": "", "Capacity:": "1.5 litres", "Power:": "3000 W", "Variable temperature control": "", "Water level indicator": ""}, "text": "KITCHENAID Artisan 5KEK1522BAC Traditional Kettle - Almond Cream", "type": "link", "variant": {"experience": "desktop", "name": ""}}
{"brand": "KENWOOD", "destination": {"path": "", "url": "/products/kenwood-abbey-lux-zjp05codg-jug-kettle-dark-grey-and-rose-gold-10226442.html"}, "locatorComponent": {"path": "listview.pdp-link.a.link", "position": 1, "section": "productTile"}, "price": "29.99", "product": "Abbey Lux ZJP05CODG Jug Kettle - Dark Grey & Rose Gold", "properties": {"360-degree rotational base": "", "Anti-limescale filter": "", "Capacity:": "1.7 litres", "Power:": "3000 W", "Water level indicator": ""}, "text": "KENWOOD Abbey Lux ZJP05CODG Jug Kettle - Dark Grey & Rose Gold", "type": "link", "variant": {"experience": "desktop", "name": ""}}
